latex_gen.pyi
latex_gen.cpython-310-x86_64-linux-gnu.so
latex_gen_z7-7.3.2202241011.dist-info/WHEEL
latex_gen_z7-7.3.2202241011.dist-info/top_level.txt
latex_gen_z7-7.3.2202241011.dist-info/RECORD
latex_gen_z7-7.3.2202241011.dist-info/METADATA
latex_gen_z7-7.3.2202241011.dist-info/zip-safe
